LICENSE
MANIFEST.in
README.rst
setup.py
django_log_analyser.egg-info/PKG-INFO
django_log_analyser.egg-info/SOURCES.txt
django_log_analyser.egg-info/dependency_links.txt
django_log_analyser.egg-info/requires.txt
django_log_analyser.egg-info/top_level.txt
log_analyser/__init__.py
log_analyser/admin.py
log_analyser/constants.py
log_analyser/models.py
log_analyser/urls.py
log_analyser/utils.py
log_analyser/views.py
log_analyser/management/__init__.py
log_analyser/management/commands/__init__.py
log_analyser/management/commands/generate_recent_rds_log_report.py
log_analyser/migrations/0001_initial.py
log_analyser/migrations/0002_dblogreportdetail_db_instance.py
log_analyser/migrations/0003_auto_20160627_1754.py
log_analyser/migrations/__init__.py