Metadata-Version: 1.1
Name: django-log-analyser
Version: 0.2.2
Summary: A simple Django app to analyse RDS logs using pgbadger.
Home-page: https://github.com/squadrun/log_analyser
Author: Ketan Bhatt
Author-email: ketanbhatt1006@gmail.com
License: MIT License
Platform: UNKNOWN
Classifier: Environment :: Web Environment
Classifier: Framework :: Django
Classifier: Framework :: Django :: 1.9
Classifier: Intended Audience :: Developers
Classifier: License :: OSI Approved :: MIT License
Classifier: Operating System :: OS Independent
Classifier: Programming Language :: Python
Classifier: Programming Language :: Python :: 2
Classifier: Programming Language :: Python :: 2.7
Classifier: Topic :: Internet :: WWW/HTTP
Classifier: Topic :: Internet :: WWW/HTTP :: Dynamic Content
